citesdoc/__init__.py
citesdoc/api_client.py
citesdoc/configuration.py
citesdoc/rest.py
citesdoc/api/__init__.py
citesdoc/api/admins_api.py
citesdoc/api/developers_api.py
citesdoc/api/public_api.py
citesdoc/models/__init__.py
citesdoc/models/base_document_type.py
citesdoc/models/conditions_type.py
citesdoc/models/document_code.py
citesdoc/models/document_entry_list_type.py
citesdoc/models/document_entry_type.py
citesdoc/models/error_model.py
citesdoc/models/general_type.py
citesdoc/models/goods_type.py
citesdoc/models/issuing_type.py
citesdoc/models/metadata_type.py
citesdoc/models/other_type.py
citesdoc/models/person_type.py
citesdoc/models/taxon_type.py
citesdoc/models/template_type.py
citesdoc/models/transaction_type.py
citesdoc/models/xfdf_field_type.py
citesdoc/models/xfdf_list_type.py
citesdoc/models/xfdf_type.py
citesdoc/models/xfdf_type_identifier.py
citesdoc/models/xfdf_type_template_file.py
test/__init__.py
test/test_admins_api.py
test/test_base_document_type.py
test/test_conditions_type.py
test/test_developers_api.py
test/test_document_code.py
test/test_document_entry_list_type.py
test/test_document_entry_type.py
test/test_error_model.py
test/test_general_type.py
test/test_goods_type.py
test/test_issuing_type.py
test/test_metadata_type.py
test/test_other_type.py
test/test_person_type.py
test/test_public_api.py
test/test_taxon_type.py
test/test_template_type.py
test/test_transaction_type.py
test/test_xfdf_field_type.py
test/test_xfdf_list_type.py
test/test_xfdf_type.py
test/test_xfdf_type_identifier.py
test/test_xfdf_type_template_file.py
sysnet_citesdoc-1.0.0.3.dist-info/LICENSE
sysnet_citesdoc-1.0.0.3.dist-info/METADATA
sysnet_citesdoc-1.0.0.3.dist-info/WHEEL
sysnet_citesdoc-1.0.0.3.dist-info/top_level.txt
sysnet_citesdoc-1.0.0.3.dist-info/RECORD
